netmind_mcpserver_mcp/__init__.py
netmind_mcpserver_mcp/server.py
netmind_mcpserver_mcp-0.1.1.dist-info/LICENSE
netmind_mcpserver_mcp-0.1.1.dist-info/METADATA
netmind_mcpserver_mcp-0.1.1.dist-info/WHEEL
netmind_mcpserver_mcp-0.1.1.dist-info/entry_points.txt
netmind_mcpserver_mcp-0.1.1.dist-info/RECORD
